Wicksell/transform.py
Wicksell-2.1.0.dist-info/LICENSE
Wicksell-2.1.0.dist-info/METADATA
Wicksell-2.1.0.dist-info/WHEEL
Wicksell-2.1.0.dist-info/top_level.txt
Wicksell-2.1.0.dist-info/RECORD
