Metadata-Version: 2.1
Name: Wicksell
Version: 2.1.0
Summary: Module for computing the Wicksell transform of continuous distributions.
Author-email: Dorian Depriester <dorian.depriester@ensam.eu>
Project-URL: Homepage, https://github.com/DorianDepriester/Wicksell-py/
Project-URL: Bug Tracker, https://github.com/DorianDepriester/Wicksell-py/issues
Classifier: Programming Language :: Python :: 3
Classifier: License :: OSI Approved :: MIT License
Classifier: Operating System :: OS Independent
Requires-Python: >=3.7
License-File: LICENSE
Requires-Dist: scipy (>=1.9.1)
Requires-Dist: numpy (>=1.20.1)
